autoclicker/__init__.py
autoclicker/funcs.py
autoclicker/main.py
autoclicker/validation.py
autoclicker-0.2.dist-info/METADATA
autoclicker-0.2.dist-info/WHEEL
autoclicker-0.2.dist-info/entry_points.txt
autoclicker-0.2.dist-info/top_level.txt
autoclicker-0.2.dist-info/RECORD
