Metadata-Version: 2.1
Name: autoclicker
Version: 0.2
Summary: A simple project to auto control mouse.
Home-page: https://github.com/Zurek92/autoclicker
Author: Dawid Żurawski
Author-email: dawid.zurawski@protonmail.com
License: UNKNOWN
Platform: UNKNOWN
Requires-Dist: click (==7.0)
Requires-Dist: pyautogui (==0.9.39)
Requires-Dist: python3-xlib (==0.15)
